README.md
setup.py
src/benatools/__init__.py
src/benatools.egg-info/PKG-INFO
src/benatools.egg-info/SOURCES.txt
src/benatools.egg-info/dependency_links.txt
src/benatools.egg-info/requires.txt
src/benatools.egg-info/top_level.txt
src/benatools/ct/__init__.py
src/benatools/ct/ct.py
src/benatools/ct/plot.py
src/benatools/gbm/__init__.py
src/benatools/gbm/fitter.py
src/benatools/gbm/opt.py
src/benatools/genetic/__init__.py
src/benatools/genetic/ga.py
src/benatools/tf/__init__.py
src/benatools/tf/attention.py
src/benatools/tf/callbacks.py
src/benatools/tf/dataset.py
src/benatools/tf/efficient_net.py
src/benatools/tf/images.py
src/benatools/tf/metrics.py
src/benatools/tf/tfrec.py
src/benatools/tf/tpu.py
src/benatools/torch/__init__.py
src/benatools/torch/efficient_net.py
src/benatools/torch/fitter.py
src/benatools/torch/loss.py
src/benatools/utils/__init__.py
src/benatools/utils/tools.py