Metadata-Version: 2.1
Name: benatools
Version: 0.0.110
Summary: Utilities package for XGBoost, CatBoost, LightGBM, Tensorflow and Pytorch
Home-page: https://github.com/benayas1/benatools
Author: Alberto Benayas
Author-email: benayas1@gmail.com
License: UNKNOWN
Platform: UNKNOWN
Classifier: Programming Language :: Python :: 3
Classifier: Programming Language :: Python :: 3.6
Classifier: Programming Language :: Python :: 3.7
Classifier: Programming Language :: Python :: 3.8
Classifier: License :: OSI Approved :: MIT License
Classifier: Operating System :: OS Independent
Requires-Python: >=3.6.0
